{
  "id": "",
  "name": "",
  "font_family": "iconfont",
  "css_prefix_text": "icon-",
  "description": "",
  "glyphs": [
    {
      "icon_id": "2076366",
      "name": " 定位2小",
      "font_class": "dingweixiao",
      "unicode": "e8ba",
      "unicode_decimal": 59578
    },
    {
      "icon_id": "5387900",
      "name": "搜索_o",
      "font_class": "sousuo_o",
      "unicode": "eb86",
      "unicode_decimal": 60294
    },
    {
      "icon_id": "10182100",
      "name": "订单",
      "font_class": "dingdan",
      "unicode": "e63a",
      "unicode_decimal": 58938
    },
    {
      "icon_id": "11372774",
      "name": "首页",
      "font_class": "shouye",
      "unicode": "e8c6",
      "unicode_decimal": 59590
    },
    {
      "icon_id": "11880766",
      "name": "右",
      "font_class": "you-copy",
      "unicode": "e637",
      "unicode_decimal": 58935
    },
    {
      "icon_id": "12796466",
      "name": "我的",
      "font_class": "wode",
      "unicode": "e63b",
      "unicode_decimal": 58939
    }
  ]
}
